aio_rmq_wss_proxy/AioRmqConsumer.py
aio_rmq_wss_proxy/AsyncServer.py
aio_rmq_wss_proxy/AsyncServerHandler.py
aio_rmq_wss_proxy/ClientsController.py
aio_rmq_wss_proxy/ClientsSender.py
aio_rmq_wss_proxy/MainServerLoop.py
aio_rmq_wss_proxy/SecuredWebsocketServerProtocol.py
aio_rmq_wss_proxy/Utils.py
aio_rmq_wss_proxy/__init__.py
aio_rmq_wss_proxy-0.0.3.dist-info/LICENSE
aio_rmq_wss_proxy-0.0.3.dist-info/METADATA
aio_rmq_wss_proxy-0.0.3.dist-info/WHEEL
aio_rmq_wss_proxy-0.0.3.dist-info/top_level.txt
aio_rmq_wss_proxy-0.0.3.dist-info/RECORD
