Metadata-Version: 2.1
Name: aio-rmq-wss-proxy
Version: 0.0.3
Summary: Asynchronous Proxy Server From RabbitMQ to WebSocket
Home-page: https://github.com/GagramanyantsA/aio_rmq_wss_proxy
Author: GagramanyantsA
Author-email: arthur_gm@mail.ru
Classifier: Programming Language :: Python :: 3
Classifier: License :: OSI Approved :: MIT License
Classifier: Operating System :: OS Independent
Requires-Python: >=3.7
License-File: LICENSE
Requires-Dist: aio-pika (==8.3.0)
Requires-Dist: websockets (==10.4)
